heaven_bml/__init__.py
heaven_bml/agent_wrappers.py
heaven_bml/github_kanban.py
heaven_bml/tree_kanban.py
heaven_bml-2.6.1.dist-info/licenses/LICENSE
mcp_server/__init__.py
mcp_server/__main__.py
mcp_server/server.py
python_functions/__init__.py
python_functions/agent_wrappers.py
python_functions/github_kanban.py
python_functions/tree_kanban.py
heaven_bml-2.6.1.dist-info/METADATA
heaven_bml-2.6.1.dist-info/WHEEL
heaven_bml-2.6.1.dist-info/entry_points.txt
heaven_bml-2.6.1.dist-info/top_level.txt
heaven_bml-2.6.1.dist-info/RECORD
